Metadata-Version: 1.1
Name: OneClickPackage
Version: 1.1
Summary: One Click Python Package Creator!
Home-page: https://github.com/DeveshAgrawal1/OneClickPackage-1.0
Author: Devesh Agrawal
Author-email: dagrawal1096@gmail.com
License: MIT
Download-URL: https://github.com/DeveshAgrawal1/OneClickPackage-1.0
Keywords: python package,create package,one click
Platform: UNKNOWN
